pomp/__init__.py
pomp/contrib/__init__.py
pomp/contrib/asynciotools.py
pomp/contrib/concurrenttools.py
pomp/contrib/item.py
pomp/contrib/pipelines.py
pomp/contrib/urllibtools.py
pomp/core/__init__.py
pomp/core/base.py
pomp/core/engine.py
pomp/core/utils.py
pomp-0.2.1.dist-info/DESCRIPTION.rst
pomp-0.2.1.dist-info/METADATA
pomp-0.2.1.dist-info/RECORD
pomp-0.2.1.dist-info/WHEEL
pomp-0.2.1.dist-info/metadata.json
pomp-0.2.1.dist-info/top_level.txt
