Metadata-Version: 2.0
Name: pomp
Version: 0.2.1
Summary: Screen scraping and web crawling framework
Home-page: http://bitbucket.org/estin/pomp
Author: Evgeniy Tatarkin
Author-email: tatarkin.evg@gmail.com
License: BSD
Platform: any
Classifier: Intended Audience :: Developers
Classifier: License :: OSI Approved :: BSD License
Classifier: Operating System :: OS Independent
Classifier: Programming Language :: Python
Classifier: Programming Language :: Python :: 2
Classifier: Programming Language :: Python :: 3
